qingping_iot_cloud/QingpingCloud.py
qingping_iot_cloud/QingpingDevice.py
qingping_iot_cloud/QingpingDeviceProperty.py
qingping_iot_cloud/__init__.py
qingping_iot_cloud-0.2.2.dist-info/METADATA
qingping_iot_cloud-0.2.2.dist-info/WHEEL
qingping_iot_cloud-0.2.2.dist-info/entry_points.txt
qingping_iot_cloud-0.2.2.dist-info/licenses/LICENSE
qingping_iot_cloud-0.2.2.dist-info/RECORD
