Metadata-Version: 2.4
Name: qingping_iot_cloud
Version: 0.2.2
Summary: Library for accessing cloud service of Qingping IoT .
Project-URL: Homepage, https://github.com/danielskowronski/qingping-iot-cloud
Project-URL: Issues, https://github.com/danielskowronski/qingping-iot-cloud/issues
Author: Daniel Skowronski
License-File: LICENSE
Classifier: License :: OSI Approved :: BSD License
Classifier: Operating System :: OS Independent
Classifier: Programming Language :: Python :: 3
Requires-Python: >=3.8
Requires-Dist: requests-oauth2client~=1.6.0
Requires-Dist: requests~=2.32.3
